CHANGELOG.rst
DESCRIPTION.rst
MANIFEST.in
README.rst
setup.py
cbc/__init__.py
cbc/__main__.py
cbc/cbhandler.py
cbc/charthandler.py
cbc/init.py
cbc/template.py
cbc/tenants.py
charts/__init__.py
charts/__main__.py
charts/init.py
charts/prep.py
charts/xlsx.py
hcpcbc.egg-info/PKG-INFO
hcpcbc.egg-info/SOURCES.txt
hcpcbc.egg-info/dependency_links.txt
hcpcbc.egg-info/entry_points.txt
hcpcbc.egg-info/requires.txt
hcpcbc.egg-info/top_level.txt