Metadata-Version: 1.1
Name: hcpcbc
Version: 2.3.1
Summary: HCP Chargeback Collection utility
Home-page: https://gitlab.com/simont3/hcpcbc
Author: Thorsten Simons
Author-email: sw@snomis.eu
License: MIT
Keywords: HCP chargeback report Hitachi Content Platform
Platform: UNKNOWN
Classifier: Development Status :: 5 - Production/Stable
Classifier: Intended Audience :: System Administrators
Classifier: Topic :: System :: Archiving
Classifier: Topic :: System :: Logging
Classifier: License :: OSI Approved :: MIT License
Classifier: Programming Language :: Python :: 3.5
Classifier: Operating System :: OS Independent
Classifier: Natural Language :: English
